pyramid_mcp/__init__.py
pyramid_mcp/cli.py
pyramid_mcp/core.py
pyramid_mcp/decorators.py
pyramid_mcp/introspection/__init__.py
pyramid_mcp/introspection/core.py
pyramid_mcp/introspection/cornice.py
pyramid_mcp/introspection/filters.py
pyramid_mcp/introspection/requests.py
pyramid_mcp/introspection/routes.py
pyramid_mcp/introspection/schemas.py
pyramid_mcp/introspection/security.py
pyramid_mcp/introspection/tools.py
pyramid_mcp/protocol.py
pyramid_mcp/schemas.py
pyramid_mcp/security.py
pyramid_mcp/version.py
pyramid_mcp/wsgi.py
pyramid_mcp-0.0.27.dist-info/METADATA
pyramid_mcp-0.0.27.dist-info/WHEEL
pyramid_mcp-0.0.27.dist-info/entry_points.txt
pyramid_mcp-0.0.27.dist-info/licenses/LICENSE
pyramid_mcp-0.0.27.dist-info/RECORD
