Metadata-Version: 2.4
Name: pyramid-mcp
Version: 0.0.27
Summary: Model Context Protocol (MCP) integration for Pyramid web framework
License: MIT
License-File: LICENSE
Keywords: pyramid,mcp,model-context-protocol,web,framework,ai,llm
Author: pyramid-mcp contributors
Requires-Python: >=3.10,<4.0
Classifier: Development Status :: 4 - Beta
Classifier: Framework :: Pyramid
Classifier: Intended Audience :: Developers
Classifier: License :: OSI Approved :: MIT License
Classifier: Operating System :: OS Independent
Classifier: Programming Language :: Python :: 3
Classifier: Programming Language :: Python :: 3.10
Classifier: Programming Language :: Python :: 3.11
Classifier: Programming Language :: Python :: 3.12
Classifier: Programming Language :: Python :: 3.13
Classifier: Programming Language :: Python :: 3.14
Classifier: Topic :: Internet :: WWW/HTTP
Classifier: Topic :: Internet :: WWW/HTTP :: WSGI :: Application
Classifier: Topic :: Scientific/Engineering :: Artificial Intelligence
Classifier: Topic :: Software Development :: Libraries :: Python Modules
Requires-Dist: click (>=8.1.0,<9.0.0)
Requires-Dist: cornice (>=6.0.0,<7.0.0)
Requires-Dist: marshmallow (>=3.22.0,<4.0.0)
Requires-Dist: pyramid (>=2.0,<3.0)
Project-URL: Documentation, https://github.com/cartaorobbin/pyramid-mcp
Project-URL: Homepage, https://github.com/cartaorobbin/pyramid-mcp
Project-URL: Repository, https://github.com/cartaorobbin/pyramid-mcp
